{"name":"Aleksandra","surname":"Rezetka","departmentID":6,"paidLeave":23,"childCareLeave":2,"multisport":false,"healtcareLeave":false,"cashPerHour":45,"password":"123"}
{"name":"Anna","surname":"Mari","departmentID":6,"paidLeave":12,"childCareLeave":1,"multisport":false,"healtcareLeave":false,"cashPerHour":30,"password":"VqRZvE9sPetf"}
{"name":"Anatole","surname":"Cabell","departmentID":6,"paidLeave":23,"childCareLeave":1,"multisport":false,"healtcareLeave":true,"cashPerHour":47,"password":"SmalA7qgc4"}
{"name":"Maciej","surname":"Adamczyk","departmentID":6,"paidLeave":8,"childCareLeave":4,"multisport":false,"healtcareLeave":false,"cashPerHour":34,"password":"HYtPpN"}
